ibflex/Types.py
ibflex/__init__.py
ibflex/__version__.py
ibflex/client.py
ibflex/enums.py
ibflex/parser.py
ibflex/py.typed
ibflex/utils.py
ibflex-0.13.dist-info/METADATA
ibflex-0.13.dist-info/RECORD
ibflex-0.13.dist-info/WHEEL
ibflex-0.13.dist-info/entry_points.txt
ibflex-0.13.dist-info/top_level.txt
