Metadata-Version: 2.1
Name: ibflex
Version: 0.13
Summary: Parse Interactive Brokers Flex XML reports and convert to Python types
Home-page: https://github.com/csingley/ibflex
Author: Christopher Singley
Author-email: csingley@gmail.com
License: MIT
Download-URL: https://github.com/csingley/ibflex/tarball/0.13
Keywords: Interactive Brokers,ibkr,flex,xml
Platform: UNKNOWN
Classifier: Development Status :: 3 - Alpha
Classifier: Intended Audience :: Developers
Classifier: Intended Audience :: Financial and Insurance Industry
Classifier: Topic :: Software Development :: Libraries :: Python Modules
Classifier: Topic :: Utilities
Classifier: Topic :: Office/Business
Classifier: Topic :: Office/Business :: Financial
Classifier: Topic :: Office/Business :: Financial :: Accounting
Classifier: Topic :: Office/Business :: Financial :: Investment
Classifier: License :: OSI Approved :: MIT License
Classifier: Operating System :: OS Independent
Classifier: Natural Language :: English
Classifier: Programming Language :: Python
Classifier: Programming Language :: Python :: 3 :: Only
Classifier: Programming Language :: Python :: 3.7
Requires-Python: >=3.7
Provides-Extra: web
Provides-Extra: web
Requires-Dist: requests; extra == 'web'
